nodeflow/__init__.py
nodeflow/adapter/__init__.py
nodeflow/adapter/abstract.py
nodeflow/adapter/pipeline.py
nodeflow/builtin/__init__.py
nodeflow/builtin/adapters/__init__.py
nodeflow/builtin/adapters/numeric.py
nodeflow/builtin/adapters/pythonic.py
nodeflow/builtin/converter.py
nodeflow/builtin/functions/__init__.py
nodeflow/builtin/functions/if_expression.py
nodeflow/builtin/variables/__init__.py
nodeflow/builtin/variables/numeric.py
nodeflow/builtin/variables/path.py
nodeflow/builtin/variables/result.py
nodeflow/converter/__init__.py
nodeflow/converter/converter.py
nodeflow/converter/func2node.py
nodeflow/dispenser/__init__.py
nodeflow/dispenser/dispenser.py
nodeflow/node/__init__.py
nodeflow/node/abstract.py
nodeflow/node/function.py
nodeflow/node/variable.py
nodeflow-0.1.1.dist-info/LICENSE
nodeflow-0.1.1.dist-info/METADATA
nodeflow-0.1.1.dist-info/WHEEL
nodeflow-0.1.1.dist-info/RECORD
