Metadata-Version: 2.3
Name: nodeflow
Version: 0.1.1
Summary: 
Author: Maksim Shushkevich
Author-email: meshushkevich@edu.hse.ru
Requires-Python: >=3.10,<4.0
Classifier: Programming Language :: Python :: 3
Classifier: Programming Language :: Python :: 3.10
Classifier: Programming Language :: Python :: 3.11
Classifier: Programming Language :: Python :: 3.12
Classifier: Programming Language :: Python :: 3.13
